ngm_remove/__init__.py
ngm_remove/db.py
ngm_remove/fileblocks.py
ngm_remove/lib.py
ngm_remove/log.py
ngm_remove/mkfile.py
ngm_remove/reflink.py
ngm_remove/utils.py
ngm_remove-0.0.13.dist-info/METADATA
ngm_remove-0.0.13.dist-info/WHEEL
ngm_remove-0.0.13.dist-info/entry_points.txt
ngm_remove-0.0.13.dist-info/RECORD
