Metadata-Version: 2.4
Name: ngm-remove
Version: 0.0.13
Summary: File tools: reflink, copy, remove, mkfile, fileblocks, filestat, filesize
Author-email: Aibulat <ngmaibulat@gmail.com>
Requires-Python: >=3.8
